fbref_package/__init__.py
fbref_package/function_package.py
fbref_package-1.5.dist-info/METADATA
fbref_package-1.5.dist-info/WHEEL
fbref_package-1.5.dist-info/top_level.txt
fbref_package-1.5.dist-info/RECORD
