Metadata-Version: 2.1
Name: fbref-package
Version: 1.5
Summary: A Python package to API Data fbref.com by Sports Data Campus
Home-page: UNKNOWN
Author: author
Author-email: ing.lucasbracamonte@gmail.com
License: UNKNOWN
Platform: UNKNOWN
Requires-Dist: pandas
Requires-Dist: sqlalchemy
Requires-Dist: mysql-connector
